atto_py-0.9.1.dist-info/licenses/LICENSE.txt
attopy/Account.py
attopy/AttoClient.py
attopy/Block.py
attopy/Entry.py
attopy/Receivable.py
attopy/Transaction.py
attopy/__init__.py
attopy/_format.py
attopy/boilerplate.py
attopy/convert.py
attopy/field_types.py
attopy/main.py
atto_py-0.9.1.dist-info/METADATA
atto_py-0.9.1.dist-info/WHEEL
atto_py-0.9.1.dist-info/top_level.txt
atto_py-0.9.1.dist-info/RECORD
